pyfembuilder/__init__.py
pyfembuilder-2.0.2.dist-info/METADATA
pyfembuilder-2.0.2.dist-info/WHEEL
pyfembuilder-2.0.2.dist-info/entry_points.txt
pyfembuilder-2.0.2.dist-info/RECORD
